{"accomplishments": {"certifications": [], "courses": [], "honors": ["Outstanding Contribution Award"], "languages": ["English", "French", "German", "Italian", "Portuguese", "Spanish"], "organizations": [], "patents": [], "projects": [], "publications": [], "test_scores": []}, "experiences": {"education": [{"activities": "None", "date_range": "1993 – 1996", "degree": "None", "field_of_study": "None", "grades": "None", "name": "Burgundy School of Business - BSB"},{"activities": "None", "date_range": "1996 – 1996", "degree": "None", "field_of_study": "None", "grades": "None", "name": "Turku School of Economics at theUniversity of Turk"},{"activities": "None", "date_range": "2016", "degree": "Level 3", "field_of_study": "None", "grades": "Level 3 Award in Wines", "name": "Wine & Spirit Education Trust"}], "jobs": [{"company": "MAISON ALBERT BICHOT", "date_range": "Jan 2019 – Present", "description": "None", "li_company_url": "https://www.linkedin.com/company/25708815/", "location": "Dijon Area, France", "title": "Chief Executive Officer"}, {"company": "Vinexpo", "date_range": "Sep 2013 – Aug 2018", "description": "None", "li_company_url": "https://www.linkedin.com/company/2856923/", "location": "Bordeaux Area, France", "title": "Chief Executive Officer"}, {"company": "Laurent-Perrier Suisse", "date_range": "Apr 2009 – Aug 2013", "description": "None", "li_company_url": "https://www.linkedin.com/company/3028101/", "location": "Geneva Area, Switzerland", "title": "Managing Director"}, {"company": "Champagne Laurent-Perrier", "date_range": "Mar 2012 – Jul 2013", "description": "None", "li_company_url": "https://www.linkedin.com/company/54786/", "location": "None", "title": "Director Asia Pacific"}, {"company": "Champagne Laurent-Perrier", "date_range": "Sep 2002 – Apr 2009", "description": "None", "li_company_url": "https://www.linkedin.com/company/54786/", "location": "Reims Area, France", "title": "Area Export Director"}, {"company": "Champagne Bollinger", "date_range": "Jan 1998 – Sep 2002", "description": "None", "li_company_url": "https://www.linkedin.com/company/2122676/", "location": "Reims Area, France", "title": "Export Manager"}], "volunteering": []}, "interests": ["luxuryhotelassociation.org| Largest group for Hospitality, "Travel, Hotels,Wellness, Food, Spa", "Relais & Châteaux", "Champagne lovers!", "European Wine Professionals", "MANAGERS OF LUXURY", "Pernod Ricard"], "personal_info": {"company": "MAISON ALBERT BICHOT", "connected": "None", "current_company_link": "https://www.linkedin.com/company/25708815/", "email": "None", "followers": "2,242", "headline": "Chief Executive Officer at Maison Albert Bichot", "image": "https://media.licdn.com/dms/image/C4E03AQGOLzbdA4xH2w/profile-displayphoto-shrink_800_800/0?e=1563408000&v=beta&t=SVDyY_dZUJ5Rs89O88A_0-8RQqZHtCPYFqHP9E8IvuI", "location": "Beaune, Burgundy, France", "name": "Guillaume Deglise", "phone": "None", "school": "None", "summary": "Experienced CEO in the wine and spiritsindustry with international background, " leadership and teamn management. Strategic thinking, brand buildingand entrepreneurial skills. Expert indistributionn n strategies, trade marketing and salesorganization. Multilingual profile and wineexpert.n ...", "websites": []}, "skills": [{"endorsements": "23", "name": "Wine Tasting"}, {"endorsements": "14", "name": "Export"}, {"endorsements": "14", "name": "Management"}, {"endorsements": "10", "name": "Public Relations"}, {"endorsements": "10", "name": "Brand Development"}, {"endorsements": "7", "name": "Brand Management"}, {"endorsements": "7", "name": "Hospitality Industry"}, {"endorsements": "7", "name": "Event Management"}, {"endorsements": "6", "name": "Negotiation"}, {"endorsements": "6", "name": "Winemaking"}, {"endorsements": "5", "name": "Trade Marketing"}, {"endorsements": "5", "name": "Wineries"}, {"endorsements": "5", "name": "Press Relations"}, {"endorsements": "4", "name": "Languages"}, {"endorsements": "4", "name": "Sales Management"}, {"endorsements": "2", "name": "Marketing Strategy"}, {"endorsements": "1", "name": "Leadership"}, {"endorsements": "1", "name": "Business Strategy"}, {"endorsements": "1", "name": "Business Development"}, {"endorsements": "1", "name": "International Marketing"}, {"endorsements": "1", "name": "Entrepreneurship"}, {"endorsements": "1", "name": "Financial Analysis"}, {"endorsements": "1", "name": "Recruiting"}, {"endorsements": "1", "name": "Project Management"}, {"endorsements": "1", "name": "Strategy"}, {"endorsements": "1", "name": "Change Management"}, {"endorsements": "1", "name": "Strategic Planning"}, {"endorsements": "1", "name": "Team Management"}, {"endorsements": "1", "name": "Wine & Spirits Industry"}, {"endorsements": "1", "name": "Launching New Brands"}, {"endorsements": "1", "name": "Press Conferences"}, {"endorsements": "1", "name": "CEO"}, {"endorsements": "1", "name": "Bilingual Communications"}]}
