{"accomplishments": {"certifications": [], "courses": [], "honors": [], "languages": [], "organizations": [], "patents": [], "projects": [], "publications": [], "test_scores": []}, "experiences": {"education": [], "jobs": [], "volunteering": []}, "interests": [], "personal_info": {"company": "Bite Squad", "connected": "None", "current_company_link": "", "email": "None", "followers": "", "headline": "Director Of Operations at Bite Squad MX", "image": "https://media.licdn.com/dms/image/C4E03AQEOlRfiQ3iguw/profile-displayphoto-shrink_800_800/0?e=1563408000&v=beta&t=KnpGdxAStUAPBW-E9a23PEyZbXjm3aitiPkpj10wJeY", "location": "Hipodromo, Mexico City, Mexico", "name": "Ilse Luna", "phone": "None", "school": "Universidad Nacional Autónoma de México", "summary": "Responsible for the implementation of businessguidelines and strategies. Reviewing workingpracticesn to ascertain their success and if not, devisean alternativexa0to ensure the businessoperates within then n "companys mission statementn" ...", "websites": ["https://www.bitesquad.com/"]}, "skills": []}
