{"accomplishments": {"certifications": [], "courses": [], "honors": [], "languages": [], "organizations": [], "patents": [], "projects": [], "publications": [], "test_scores": []}, "experiences": {"education": [], "jobs": [{"company": "De Bernt Entschev Human Capital", "date_range": "Apr 2010 – Present", "description": "Headhunter | Executive Search |Assessment | Outplacement |Downsizingn ... See more", "li_company_url": "https://www.linkedin.com/company/135220/", "location": "Brasil", "title": "Headhunter"}, {"company": "GPTI Tecnologia da Informação", "date_range": "Apr 2004 – Apr 2010", "description": "None", "li_company_url": "https://www.linkedin.com/company/10387/", "location": "São Paulo e Curitiba", "title": "Analista de Recursos Humanos"}], "volunteering": []}, "interests": ["Human Resources (HR) & Talent Management Executive", "Sogefi Group", "GRUPO DE EXECUTIVOS DO BRASIL", "UFPR", "McKinsey & Company", "Strategic Business and Competitive Intelligence Professionals"], "personal_info": {"company": "De Bernt Entschev Human Capital", "connected": "None", "current_company_link": "https://www.linkedin.com/company/135220/", "email": "None", "followers": "23,421", "headline": "Headhunter", "image": "https://media.licdn.com/dms/image/C4D03AQFttj5sF6BX2w/profile-displayphoto-shrink_800_800/0?e=1563408000&v=beta&t=FP8LhhCaq30SuNB_2lsQzLZZWldvDwusdWKOGJc6E2Q", "location": "São Paulo Area, Brazil", "name": "Jéssica Monteiro", "phone": "None", "school": "None", "summary": "Headhunter | Executive Search | Assessment |Outplacement | Downsizingn ...", "websites": []}, "skills": [{"endorsements": 0, "name": "Outplacement"}, {"endorsements": 0, "name": "Executive Search"}, {"endorsements": 0, "name": "Outsourcing"}, {"endorsements": 0, "name": "Psychological Assessment"}, {"endorsements": 0, "name": "Downsizing"}, {"endorsements": 0, "name": "Headhunters"}]}
