{"accomplishments": {"certifications": [], "courses": [], "honors": [], "languages": ["Español", "Inglés", "Italiano", "Neerlandés"], "organizations": [], "patents": [], "projects": ["Startup Global Jamt Corporation"], "publications": [], "test_scores": []}, "experiences": {"education": [{"activities": "None", "date_range": "2014 – 2016", "degree": "Técnico en negocios internacionales", "field_of_study": "Administración de negociosinternacionales", "grades": "None", "name": "ADEX"},{"activities": "None", "date_range": "2014 – 2015", "degree": "None", "field_of_study": "None", "grades": "None", "name": "Privateacher"}], "jobs": [{"company": "Global Jamt Corporation S.A.C.", "date_range": "Oct 2015 – Present", "description": "Socia fundadora de Startup GlobalJamt Corporation S.A.C. dedicada ala comercialización yn n exportación de frutas, " hortalizas, granos yagroindustriales.n ... See more", "li_company_url": "", "location": "Lima Province, Per", "title": "Gerente de operaciones"}], "volunteering": [{"cause": "None", "company": "Techo - Perú", "date_range": "Mar 2012 – Feb 2014", "description": "None", "location": "None", "title": "Coordinador logístico"}]}, "interests": ["Fruits & Vegetables Europe & Russia Distribution", "Agroindustrias AIB", "Harvard Business Review", "Future of Agriculture", "Euromonitor International", "TED Conferences"], "personal_info": {"company": "Global Jamt Corporation S.A.C.", "connected": "None", "current_company_link": "", "email": "None", "followers": "", "headline": "COO at Global Jamt Corp.", "image": "https://media.licdn.com/dms/image/C4D03AQFmTftbWCdsaQ/profile-displayphoto-shrink_800_800/0?e=1563408000&v=beta&t=VPtgIrdGFg0aG-M2kZW4W3QoH2WbMWBLZq0fx4xFeTA", "location": "Per", "name": "Virginia Reyes Silva", "phone": "None", "school": "ADEX", "summary": "Administradorade negocios internacionales;con sólidos conocimientos en la sintetizaciónen interpretación de datos e información deinteligencia comercial para mercadosextranjeros así como lan n elaboración de planes de exportación ygestión de proyectos.n ...", "websites": []}, "skills": []}
